Metadata-Version: 2.1
Name: numpy-ops1234567890
Version: 1.0.0
Summary: A simple package to do numpy power operation
Author: Rahul Jha
License: BSD
